ClassifyGene/Classify.py
ClassifyGene/__init__.py
exDEG/Classify.py
exDEG/__init__.py
exDEG-1.0.0.dist-info/METADATA
exDEG-1.0.0.dist-info/RECORD
exDEG-1.0.0.dist-info/WHEEL
exDEG-1.0.0.dist-info/top_level.txt
